highctidh
highctidh_1024
highctidh_2048
highctidh_511
highctidh_512
