Metadata-Version: 2.1
Name: highctidh
Version: 1.0.2023121101
Summary: ctype bindings for highctidh
Home-page: https://codeberg.org/vula/highctidh
Author: Jacob Appelbaum
Author-email: jacob@appelbaum.net
Maintainer: Jacob Appelbaum
Maintainer-email: jacob@appelbaum.net
License: Public Domain
Project-URL: Documentation, https://codeberg.org/vula/highctidh
Project-URL: Source, https://codeberg.org/vula/highctidh
Keywords: post-quantum cryptography,cryptography,csidh,ctidh
Requires-Python: >=3.10.4
License-File: AUTHORS.md
Provides-Extra: test
Requires-Dist: pytest; extra == "test"
